smsit/__init__.py
smsit/exceptions.py
smsit/gateway.py
smsit/manager.py
smsit/message.py
smsit/gateways/__init__.py
smsit/gateways/dummy.py
smsit/gateways/ghasedak.py
smsit/gateways/niksms.py
smsit/gateways/smsmagic.py
smsit-1.0.3.dist-info/LICENSE
smsit-1.0.3.dist-info/METADATA
smsit-1.0.3.dist-info/WHEEL
smsit-1.0.3.dist-info/top_level.txt
smsit-1.0.3.dist-info/RECORD
